{
  "competencia": "2026-05",
  "gerado_em": "2026-05-05T04:47:00.085852",
  "quantidade_total": 21,
  "valor_total": 2291.0,
  "valor_total_descontado": 916.0,
  "valor_total_pendente": 1375.0,
  "por_unidade": [
    {
      "unidade": "Bento",
      "quantidade": 1,
      "valor": 105.0
    },
    {
      "unidade": "Caxias",
      "quantidade": 8,
      "valor": 811.0
    },
    {
      "unidade": "Encantado",
      "quantidade": 9,
      "valor": 1040.0
    },
    {
      "unidade": "Soledade",
      "quantidade": 3,
      "valor": 335.0
    }
  ],
  "por_doutor": [
    {
      "doutor": "Ana Cristina Corso",
      "quantidade": 2,
      "valor_descontado": 208.0
    },
    {
      "doutor": "Cristian Pressi",
      "quantidade": 3,
      "valor_descontado": 0.0
    },
    {
      "doutor": "Franciele Pedrotti",
      "quantidade": 6,
      "valor_descontado": 603.0
    },
    {
      "doutor": "Naiane Pieta",
      "quantidade": 1,
      "valor_descontado": 105.0
    },
    {
      "doutor": "Renata Protto",
      "quantidade": 9,
      "valor_descontado": 0.0
    }
  ]
}