{
  "competencia": "2026-04",
  "gerado_em": "2026-04-07T10:44:17.559341",
  "quantidade_total": 0,
  "valor_total": 0,
  "valor_total_descontado": 0,
  "valor_total_pendente": 0,
  "por_unidade": [],
  "por_doutor": [],
  "2026-04": {
    "competencia": "2026-04",
    "gerado_em": "2026-04-10T14:10:26.972412",
    "quantidade_total": 152,
    "valor_total": 19358.0,
    "valor_total_descontado": 3700.0,
    "valor_total_pendente": 15658.0,
    "por_unidade": [
      {
        "unidade": "Bento",
        "quantidade": 3,
        "valor": 250.0
      },
      {
        "unidade": "Caxias",
        "quantidade": 37,
        "valor": 4827.0
      },
      {
        "unidade": "Encantado",
        "quantidade": 2,
        "valor": 200.0
      },
      {
        "unidade": "Farroupilha",
        "quantidade": 15,
        "valor": 2218.0
      },
      {
        "unidade": "FloresDaCunha",
        "quantidade": 14,
        "valor": 1978.0
      },
      {
        "unidade": "Garibaldi",
        "quantidade": 27,
        "valor": 3192.0
      },
      {
        "unidade": "Soledade",
        "quantidade": 46,
        "valor": 5754.0
      },
      {
        "unidade": "Ssdocai",
        "quantidade": 8,
        "valor": 939.0
      }
    ],
    "por_doutor": [
      {
        "doutor": "Adriele da Silva",
        "quantidade": 5,
        "valor_descontado": 0.0
      },
      {
        "doutor": "Cristian Pressi",
        "quantidade": 29,
        "valor_descontado": 0.0
      },
      {
        "doutor": "Dionathan Pohlmann",
        "quantidade": 16,
        "valor_descontado": 2188.0
      },
      {
        "doutor": "Everlize Cipriani",
        "quantidade": 7,
        "valor_descontado": 0.0
      },
      {
        "doutor": "Franciele Pedrotti",
        "quantidade": 10,
        "valor_descontado": 0.0
      },
      {
        "doutor": "Gabrielli Fabonato",
        "quantidade": 2,
        "valor_descontado": 0.0
      },
      {
        "doutor": "Gislaine Santos",
        "quantidade": 5,
        "valor_descontado": 487.0
      },
      {
        "doutor": "Jéssica Barreto",
        "quantidade": 3,
        "valor_descontado": 250.0
      },
      {
        "doutor": "Leandro Diniz",
        "quantidade": 3,
        "valor_descontado": 0.0
      },
      {
        "doutor": "Luisa Moraes Lucas",
        "quantidade": 15,
        "valor_descontado": 0.0
      },
      {
        "doutor": "Marcella Zancanaro",
        "quantidade": 5,
        "valor_descontado": 575.0
      },
      {
        "doutor": "Nelson Vaccari",
        "quantidade": 1,
        "valor_descontado": 0.0
      },
      {
        "doutor": "Sofie Owens",
        "quantidade": 19,
        "valor_descontado": 0.0
      },
      {
        "doutor": "Tamara Macanan",
        "quantidade": 27,
        "valor_descontado": 0.0
      },
      {
        "doutor": "Thiany Cristofoli",
        "quantidade": 2,
        "valor_descontado": 200.0
      },
      {
        "doutor": "TOP",
        "quantidade": 3,
        "valor_descontado": 0.0
      }
    ]
  }
}